coap/__init__.py
coap/coap.py
coap/coapDefines.py
coap/coapException.py
coap/coapMessage.py
coap/coapObjectSecurity.py
coap/coapOption.py
coap/coapResource.py
coap/coapTokenizer.py
coap/coapTransmitter.py
coap/coapUri.py
coap/coapUtils.py
coap/coapVersion.py
coap/socketUdp.py
coap/socketUdpDispatcher.py
coap/socketUdpReal.py
openwsn_coap-0.0.8.dist-info/COPYING.txt
openwsn_coap-0.0.8.dist-info/METADATA
openwsn_coap-0.0.8.dist-info/WHEEL
openwsn_coap-0.0.8.dist-info/top_level.txt
openwsn_coap-0.0.8.dist-info/RECORD
