Metadata-Version: 2.1
Name: openwsn-coap
Version: 0.0.8
Summary: A CoAP Python library
Home-page: http://www.openwsn.org/
Author: Thomas Watteyne
Author-email: watteyne@eecs.berkeley.edu
License: /*
Keywords: CoAP,Internet of Things,IETF CORE
Platform: platform-independent
Classifier: Development Status :: 1 - Planning
Classifier: Intended Audience :: Developers
Classifier: License :: OSI Approved :: BSD License
Classifier: Operating System :: OS Independent
Classifier: Programming Language :: Python
Classifier: Programming Language :: Python :: 3
Classifier: Topic :: Communications
Classifier: Topic :: Home Automation
Classifier: Topic :: Internet
Classifier: Topic :: Software Development
Classifier: Topic :: Software Development :: Libraries
Classifier: Topic :: Software Development :: Libraries :: Python Modules
Requires-Python: >=3.6
Requires-Dist: scons
Requires-Dist: PyDispatcher
Requires-Dist: pylint
Requires-Dist: pycryptodome
Requires-Dist: cbor
Requires-Dist: hkdf
Requires-Dist: pytest
